{
  "main": {
    "id": "3c2396c1e50aebbf",
    "type": "split",
    "children": [
      {
        "id": "473f050a83cb3a7a",
        "type": "tabs",
        "children": [
          {
            "id": "1cf3d5a74686f5e0",
            "type": "leaf",
            "state": {
              "type": "markdown",
              "state": {
                "file": "Frontend/Angular/Udemy/Section 2 - Angular Essentials - Components, Templates, Services and More/21. Outputting Dynamic Content with String Interpolation/0. Index.md",
                "mode": "source",
                "source": false
              },
              "icon": "lucide-file",
              "title": "0. Index"
            }
          }
        ]
      }
    ],
    "direction": "vertical"
  },
  "left": {
    "id": "37c04dffdb68444c",
    "type": "split",
    "children": [
      {
        "id": "54a49d5e231b965a",
        "type": "tabs",
        "children": [
          {
            "id": "136b65c4bb4a1d44",
            "type": "leaf",
            "state": {
              "type": "file-explorer",
              "state": {
                "sortOrder": "alphabetical",
                "autoReveal": false
              },
              "icon": "lucide-folder-closed",
              "title": "Explorador de arquivos"
            }
          },
          {
            "id": "f0f01073b6070477",
            "type": "leaf",
            "state": {
              "type": "search",
              "state": {
                "query": "Uma empresa de tecnologia, está desenvolvendo um sistema de mensagens internas utilizando a",
                "matchingCase": false,
                "explainSearch": false,
                "collapseAll": false,
                "extraContext": false,
                "sortOrder": "alphabetical"
              },
              "icon": "lucide-search",
              "title": "Procurar"
            }
          },
          {
            "id": "1200950d7e82c30e",
            "type": "leaf",
            "state": {
              "type": "bookmarks",
              "state": {},
              "icon": "lucide-bookmark",
              "title": "Marcadores"
            }
          }
        ]
      }
    ],
    "direction": "horizontal",
    "width": 323.5
  },
  "right": {
    "id": "ed5c23ef13420e73",
    "type": "split",
    "children": [
      {
        "id": "cd5d1f0e1bde8397",
        "type": "tabs",
        "children": [
          {
            "id": "4591da669db22a6a",
            "type": "leaf",
            "state": {
              "type": "backlink",
              "state": {
                "file": "Bem-vindo.md",
                "collapseAll": false,
                "extraContext": false,
                "sortOrder": "alphabetical",
                "showSearch": false,
                "searchQuery": "",
                "backlinkCollapsed": false,
                "unlinkedCollapsed": true
              },
              "icon": "links-coming-in",
              "title": "Links inversos para Bem-vindo"
            }
          },
          {
            "id": "772fa79470a38acc",
            "type": "leaf",
            "state": {
              "type": "outgoing-link",
              "state": {
                "file": "Bem-vindo.md",
                "linksCollapsed": false,
                "unlinkedCollapsed": true
              },
              "icon": "links-going-out",
              "title": "Links de saída para Bem-vindo"
            }
          },
          {
            "id": "a2e2c9d447b70e46",
            "type": "leaf",
            "state": {
              "type": "tag",
              "state": {
                "sortOrder": "frequency",
                "useHierarchy": true,
                "showSearch": false,
                "searchQuery": ""
              },
              "icon": "lucide-tags",
              "title": "Tags"
            }
          },
          {
            "id": "013348a8900dc1c7",
            "type": "leaf",
            "state": {
              "type": "outline",
              "state": {
                "file": "Bem-vindo.md",
                "followCursor": false,
                "showSearch": false,
                "searchQuery": ""
              },
              "icon": "lucide-list",
              "title": "Sumário de Bem-vindo"
            }
          }
        ]
      }
    ],
    "direction": "horizontal",
    "width": 300,
    "collapsed": true
  },
  "left-ribbon": {
    "hiddenItems": {
      "bases:Criar nova base": false,
      "switcher:Abrir a troca rápida": false,
      "graph:Abrir visualização em gráfico": false,
      "canvas:Criar novo canvas": false,
      "daily-notes:Abrir a nota de hoje": false,
      "templates:Inserir modelo": false,
      "command-palette:Abrir paleta de comandos": false,
      "obsidian-git:Open Git source control": false,
      "iconic:Open rulebook": false
    }
  },
  "active": "1cf3d5a74686f5e0",
  "lastOpenFiles": [
    "Frontend/Angular/Udemy/Section 2 - Angular Essentials - Components, Templates, Services and More/20. Storing Data in a Component Class/0. Index.md",
    "Frontend/Angular/Udemy/Section 2 - Angular Essentials - Components, Templates, Services and More/19. Preparing User Data (To Output Dynamic Content)/0. Index.md",
    "Frontend/Angular/Udemy/Section 2 - Angular Essentials - Components, Templates, Services and More/18. Styling and Using Our Next Custom Component/0. Index.md",
    "Frontend/Angular/Udemy/Section.md",
    "Frontend/Angular/Udemy/Section 2 - Angular Essentials - Components, Templates, Services and More/17. Managing and Creating Components with the Angular CLI/0. Index.md",
    "Frontend/Angular/Udemy/Section 2 - Angular Essentials - Components, Templates, Services and More/16. Styling the Header Component and Adding An Image/0. Index.md",
    "Frontend/Angular/Udemy/Section 2 - Angular Essentials - Components, Templates, Services and More/15. Using the Custom Component/0. Index.md",
    "Frontend/Angular/Udemy/Section 2 - Angular Essentials - Components, Templates, Services and More/14. Configuring the Custom Component/0. Index.md",
    "Frontend/Angular/Udemy/Section 2 - Angular Essentials - Components, Templates, Services and More/13. [Optional] JavaScript Refresher - Classes, Properties and More/0. Index.md",
    "Frontend/Angular/Udemy/Section 2 - Angular Essentials - Components, Templates, Services and More/12. Creating a First Custom Component/0. Index.md",
    "Frontend/Angular/Udemy/Section 2 - Angular Essentials - Components, Templates, Services and More/11. Understanding Components and How Content Ends Up On The Screen/0. Index.md",
    "Frontend/Angular/Udemy/Section 1 - Getting Started/4. Angular's Evolution and Stability/0. Index.md",
    "Frontend/Angular/Udemy/Section 1 - Getting Started/5. Creating A New Angular Project/0. Index.md",
    "Frontend/Angular/Udemy/Section 1 - Getting Started/7. About This Course/0. Index.md",
    "Frontend/Angular/Udemy/Section 2 - Angular Essentials - Components, Templates, Services and More/10. A New Starting Project and Analyzing The Project Structure/0. Index.md",
    "Frontend/Angular/Udemy/Section 2 - Angular Essentials - Components, Templates, Services and More/9. Module Introduction/0. Index.md",
    "Frontend/Angular/Udemy/Section 1 - Getting Started/8. Course Setup and Resources/0. Index.md",
    "Frontend/Angular/Udemy/Section 1 - Getting Started/0. Index.md",
    "Frontend/Angular/Udemy/Section 1 - Getting Started/6. Setting Up An Angular Development Environment/0. Index.md",
    "Frontend/Angular/Udemy/Section 1 - Getting Started/3. Why Would You Use Angular/0. Index.md",
    "Frontend/Angular/Udemy/Section 1 - Getting Started/2. What Exactly Is Angular/0. Index.md",
    "Frontend/Angular/Udemy/Section 1 - Getting Started/1. Welcome To The Course/0. Index.md",
    "Frontend/Angular/Udemy/0. Index.md",
    "Frontend/Angular/Udemy/0. Index vtt.md",
    "Frontend/Angular/Udemy/0. Index (copy).md",
    "Frontend/Angular/Udemy/Section 9 - Understanding Services and Dependency Injection - Deep Dive/0. Index.md",
    "Frontend/Angular/Udemy/Udemy/Section 00/curriculum_items.json",
    "Frontend/Angular/Udemy/Udemy/Section 00/index.json",
    "Frontend/Angular/Udemy/Section 2 - Angular Essentials - Components, Templates, Services and More/19. Preparing User Data (To Output Dynamic Content)/users/user-4.jpg",
    "Frontend/Angular/Udemy/Section 2 - Angular Essentials - Components, Templates, Services and More/19. Preparing User Data (To Output Dynamic Content)/users/user-5.jpg",
    "Frontend/Angular/Udemy/Section 2 - Angular Essentials - Components, Templates, Services and More/19. Preparing User Data (To Output Dynamic Content)/users/user-6.jpg",
    "Frontend/Angular/Udemy/Section 2 - Angular Essentials - Components, Templates, Services and More/19. Preparing User Data (To Output Dynamic Content)/users/user-3.jpg",
    "Frontend/Angular/Udemy/Section 2 - Angular Essentials - Components, Templates, Services and More/19. Preparing User Data (To Output Dynamic Content)/users/user-2.jpg",
    "Frontend/Angular/Udemy/Section 2 - Angular Essentials - Components, Templates, Services and More/19. Preparing User Data (To Output Dynamic Content)/users/user-1.jpg",
    "Frontend/Angular/Udemy/Section 2 - Angular Essentials - Components, Templates, Services and More/19. Preparing User Data (To Output Dynamic Content)/users",
    "Frontend/Angular/Udemy/Section 2 - Angular Essentials - Components, Templates, Services and More/19. Preparing User Data (To Output Dynamic Content)/users.zip",
    "Frontend/Angular/Udemy/Section 2 - Angular Essentials - Components, Templates, Services and More/16. Styling the Header Component and Adding An Image/Resources",
    "Frontend/Angular/Udemy/Udemy/Section 00/Course_ Angular - The Complete Guide (2025 Edition) _ Udemy Business_files/logo-ub-inverted.svg",
    "Frontend/Angular/Udemy/Section 42 - Angular Animations/Resources/code-snapshots/code-snapshots/ngrx-08-finished-modern/ngrx-08-finished-modern/src/app/recipes/recipe-list/recipe-item/recipe-item.component.ts",
    "Frontend/Angular/Udemy/Section 42 - Angular Animations/Resources/code-snapshots/code-snapshots/ngrx-08-finished-modern/ngrx-08-finished-modern/src/app/recipes/recipe-list/recipe-item/recipe-item.component.html",
    "Frontend/Angular/Udemy/Section 42 - Angular Animations/Resources/code-snapshots/code-snapshots/ngrx-08-finished-modern/ngrx-08-finished-modern/src/app/recipes/recipe-list/recipe-item/recipe-item.component.css",
    "Frontend/Angular/Udemy/Section 42 - Angular Animations/Resources/code-snapshots/code-snapshots/ngrx-08-finished-modern/ngrx-08-finished-modern/src/app/shopping-list/store/shopping-list.reducer.ts",
    "Frontend/Angular/Udemy/Section 42 - Angular Animations/Resources/code-snapshots/code-snapshots/ngrx-08-finished-modern/ngrx-08-finished-modern/src/app/shopping-list/store/shopping-list.actions.ts",
    "Frontend/Angular/Udemy/Udemy/Section 00/Course_ Angular - The Complete Guide (2025 Edition) _ Udemy Business_files/udemy-logo.png",
    "Frontend/Angular/Udemy/Udemy/Section 00/Course_ Angular - The Complete Guide (2025 Edition) _ Udemy Business_files/thumb-sprites.jpg",
    "Frontend/Angular/Udemy/Udemy/Section 00/Course_ Angular - The Complete Guide (2025 Edition) _ Udemy Business_files/powered_by_logo.svg"
  ]
}